COPASI/_COPASI.cp312-win_amd64.pyd
COPASI/__init__.py
python_copasi-4.46.300.dist-info/licenses/LICENSE
python_copasi-4.46.300.dist-info/METADATA
python_copasi-4.46.300.dist-info/WHEEL
python_copasi-4.46.300.dist-info/top_level.txt
python_copasi-4.46.300.dist-info/RECORD
