Metadata-Version: 2.4
Name: python-copasi
Version: 4.46.300
Summary: COPASI Python API
Home-page: http://copasi.org
Author: COPASI Team
Author-email: copasi-devel@copasi.org
License: Artistic License
License-File: LICENSE
Dynamic: author
Dynamic: author-email
Dynamic: description
Dynamic: home-page
Dynamic: license
Dynamic: license-file
Dynamic: summary
